Metadata-Version: 2.1
Name: ssh-session-manager
Version: 0.5.1
Summary: Execute commands on multiple remote SSH sessions
Home-page: https://github.com/SYSCON-International/ssh-session-manager
Author: SYSCON International
Author-email: dev@syscon-intl.com
License: UNKNOWN
Platform: UNKNOWN
Classifier: Programming Language :: Python :: 3
Classifier: License :: OSI Approved :: MIT License
Classifier: Operating System :: OS Independent
Requires-Python: >=3.7
